data_sync/__init__.py
data_sync/sync.py
data_sync/test.py
data_sync/utils/__init__.py
data_sync/utils/db_util.py
data_sync/utils/glue_util.py
data_sync/utils/hadoop_util.py
data_sync/utils/hive_util.py
data_sync/utils/msg_util.py
data_sync/utils/s3_util.py
data_sync/utils/spark_util.py
data_sync-1.2.1.dist-info/METADATA
data_sync-1.2.1.dist-info/WHEEL
data_sync-1.2.1.dist-info/top_level.txt
data_sync-1.2.1.dist-info/RECORD
