Metadata-Version: 2.1
Name: data-sync
Version: 1.2.1
Summary: sync
Home-page: UNKNOWN
Author: wangbin,weiyuhua
Author-email: binwang01@clubfactory.com
License: UNKNOWN
Platform: UNKNOWN
